{"key":"content:en:video-courses:index.md","generatedAt":"2022-04-22T12:57:54.708Z","mtime":"2022-04-22T12:57:54.692Z","slug":"","title":"Video Courses","position":"999999990000","to":"/video-courses","draft":false,"page":true,"language":"en","template":"blog","description":"Discover and learn more about the Nuxt Framework with free and premium video courses.","empty":false,"body":{"raw":"---\ntemplate: blog\ntitle: 'Video Courses'\ndescription: 'Discover and learn more about the Nuxt Framework with free and premium video courses.'\n---\n::video-courses-list\n---\nvideo-courses:\n  one:\n    title: Learn Nuxt by Building a Real World App\n    description: Learn how to build robust, modern websites with Nuxt from scratch. Or improve your website performance, code quality, while making better use of the framework.\n    image: /img/video-courses/mastering_nuxt.png\n    link: 'https://masteringnuxt.com/?utm_source=nuxt&utm_medium=link&utm_campaign=nsite'\n    tier: Premium\n  two:\n    title: Get Started with Nuxt\n    description: Learn the essentials for how to build and deploy a Nuxt site including dynamic routes, data fetching, SEO, lazy loading, global styles and transitions as well as how to generate and deploy your Nuxt app.\n    image: /img/video-courses/jamstack_explorer.png\n    link: 'https://explorers.netlify.com/learn/get-started-with-nuxt'\n    tier: Free\n  three:\n    title: Learn Nuxt with Debbie\n    description: A playlist of YouTube videos covering all things Nuxt including short videos and live streams.\n    image: /img/video-courses/learn_nuxt_with_debbie.png\n    link: 'https://www.youtube.com/c/DebbieOBrien'\n    tier: Free\n  four:\n    title: Building Applications with Vue & Nuxt\n    description: Build dynamic web applications with Vue and Nuxt! Throughout the course you’ll build out a variety of projects leveraging the tools in the Vue ecosystem including the Vue CLI, Nuxt, Vuex Store, and more.\n    image: /img/video-courses/building_applications_fe_masters.png\n    link: 'https://frontendmasters.com/courses/vue-nuxt-apps/'\n    tier: Premium\n  five:\n    title: Build a Job Board with Laravel, GraphQL, Nuxt and Apollo\n    description: Learn while you build a GraphQL API with Laravel Lighthouse, then build a Nuxt frontend with Apollo to consume it. All styled with Tailwind.\n    image: /img/video-courses/job_board.png\n    link: 'https://codecourse.com/courses/build-a-job-board-with-laravel-graphql-nuxt-and-apollo'\n    tier: Premium\n  six:\n    title: Nuxt - Vue.js on Steroids\n    description: Build highly engaging Vue JS apps with Nuxt. Nuxt adds easy server-side-rendering and a folder-based config approach.\n    image: /img/video-courses/vuejs_on_steroids.png\n    link: 'https://www.udemy.com/course/nuxtjs-vuejs-on-steroids/'\n    tier: Premium\n  seven:\n    title: Scaling Vue with Nuxt\n    description: Once you are comfortable with Vue, learning a framework like Nuxt allows you to create production-ready web apps which follow best practices.\n    image: /img/video-courses/scaling_vue_with_nuxt.png\n    link: 'https://www.vuemastery.com/courses/scaling-vue-with-nuxt-js/why-use-nuxt'\n    tier: Premium\n  eight:\n    title: Nuxt Fundamentals\n    description: Learn the fundamentals of Nuxt in this course that we created together with the founders of Nuxt. The course covers what you need to know from scaffolding to deploying your first Nuxt application.\n    image: /img/video-courses/nuxt_fundamentals.png\n    link: 'https://vueschool.io/courses/nuxtjs-fundamentals?friend=nuxt&utm_source=Nuxtjs.org&utm_medium=Link&utm_content=Courses&utm_campaign=nuxtjs-fundamentals'\n    tier: Free\n  nine:\n    title: Create a News App with Vue.js and Nuxt\n    description: You will learn how to create dynamic pages for each section of your application and load, store, display, filter, and style the data. Then end result will be a News app with multiple category pages, comments for each section, and user pages.\n    image: /img/video-courses/news_app.png\n    link: 'https://egghead.io/courses/create-a-news-app-with-vue-js-and-nuxt'\n    tier: Free\n---\n::\n","ast":{"type":"root","children":[{"type":"element","tag":"video-courses-list","props":{":video-courses":"{\"one\":{\"title\":\"Learn Nuxt by Building a Real World App\",\"description\":\"Learn how to build robust, modern websites with Nuxt from scratch. Or improve your website performance, code quality, while making better use of the framework.\",\"image\":\"/img/video-courses/mastering_nuxt.png\",\"link\":\"https://masteringnuxt.com/?utm_source=nuxt&utm_medium=link&utm_campaign=nsite\",\"tier\":\"Premium\"},\"two\":{\"title\":\"Get Started with Nuxt\",\"description\":\"Learn the essentials for how to build and deploy a Nuxt site including dynamic routes, data fetching, SEO, lazy loading, global styles and transitions as well as how to generate and deploy your Nuxt app.\",\"image\":\"/img/video-courses/jamstack_explorer.png\",\"link\":\"https://explorers.netlify.com/learn/get-started-with-nuxt\",\"tier\":\"Free\"},\"three\":{\"title\":\"Learn Nuxt with Debbie\",\"description\":\"A playlist of YouTube videos covering all things Nuxt including short videos and live streams.\",\"image\":\"/img/video-courses/learn_nuxt_with_debbie.png\",\"link\":\"https://www.youtube.com/c/DebbieOBrien\",\"tier\":\"Free\"},\"four\":{\"title\":\"Building Applications with Vue & Nuxt\",\"description\":\"Build dynamic web applications with Vue and Nuxt! Throughout the course you’ll build out a variety of projects leveraging the tools in the Vue ecosystem including the Vue CLI, Nuxt, Vuex Store, and more.\",\"image\":\"/img/video-courses/building_applications_fe_masters.png\",\"link\":\"https://frontendmasters.com/courses/vue-nuxt-apps/\",\"tier\":\"Premium\"},\"five\":{\"title\":\"Build a Job Board with Laravel, GraphQL, Nuxt and Apollo\",\"description\":\"Learn while you build a GraphQL API with Laravel Lighthouse, then build a Nuxt frontend with Apollo to consume it. All styled with Tailwind.\",\"image\":\"/img/video-courses/job_board.png\",\"link\":\"https://codecourse.com/courses/build-a-job-board-with-laravel-graphql-nuxt-and-apollo\",\"tier\":\"Premium\"},\"six\":{\"title\":\"Nuxt - Vue.js on Steroids\",\"description\":\"Build highly engaging Vue JS apps with Nuxt. Nuxt adds easy server-side-rendering and a folder-based config approach.\",\"image\":\"/img/video-courses/vuejs_on_steroids.png\",\"link\":\"https://www.udemy.com/course/nuxtjs-vuejs-on-steroids/\",\"tier\":\"Premium\"},\"seven\":{\"title\":\"Scaling Vue with Nuxt\",\"description\":\"Once you are comfortable with Vue, learning a framework like Nuxt allows you to create production-ready web apps which follow best practices.\",\"image\":\"/img/video-courses/scaling_vue_with_nuxt.png\",\"link\":\"https://www.vuemastery.com/courses/scaling-vue-with-nuxt-js/why-use-nuxt\",\"tier\":\"Premium\"},\"eight\":{\"title\":\"Nuxt Fundamentals\",\"description\":\"Learn the fundamentals of Nuxt in this course that we created together with the founders of Nuxt. The course covers what you need to know from scaffolding to deploying your first Nuxt application.\",\"image\":\"/img/video-courses/nuxt_fundamentals.png\",\"link\":\"https://vueschool.io/courses/nuxtjs-fundamentals?friend=nuxt&utm_source=Nuxtjs.org&utm_medium=Link&utm_content=Courses&utm_campaign=nuxtjs-fundamentals\",\"tier\":\"Free\"},\"nine\":{\"title\":\"Create a News App with Vue.js and Nuxt\",\"description\":\"You will learn how to create dynamic pages for each section of your application and load, store, display, filter, and style the data. Then end result will be a News app with multiple category pages, comments for each section, and user pages.\",\"image\":\"/img/video-courses/news_app.png\",\"link\":\"https://egghead.io/courses/create-a-news-app-with-vue-js-and-nuxt\",\"tier\":\"Free\"}}"},"children":[]}]},"toc":{"title":"","searchDepth":2,"depth":2,"links":[]}}}