{"key":"content:zh:index.md","generatedAt":"2022-04-21T11:59:26.913Z","mtime":"2022-04-21T11:59:26.882Z","slug":"","title":"The Intuitive Vue Framework","position":"999900000000","to":"/","draft":false,"page":true,"language":"zh","template":"blank","description":"Build your next Vue.js application with confidence using Nuxt. An open source framework making web development simple and powerful.","bgClass":"bg-white","empty":false,"body":{"raw":"---\ntemplate: blank\ntitle: 'The Intuitive Vue Framework'\ndescription: 'Build your next Vue.js application with confidence using Nuxt. An open source framework making web development simple and powerful.'\nbgClass: 'bg-white'\n---\n\n::home-hero\n#title\nThe Intuitive Vue<br>Framework\n\n#description\nBuild your next Vue.js application with confidence using Nuxt.<br class=\"hidden sm:block\" /> An open source framework making web development simple and powerful.\n\n#primary-button\n:app-button[39K+ GitHub stars]{ href=\"https://github.com/nuxt/nuxt.js\" icon=\"IconGitHub\" extraClass=\"text-white bg-sky-black hover:bg-sky-darker leading-4\" }\n\n#secondary-button\n:app-button[Get started]{ to=\"/docs/get-started/installation\" }\n::\n\n::home-learn-master\n---\ncategory: Learn\n---\n\n#title\n[Easy]{.text-primary} to learn. [Easy]{.text-primary} to master\n\n#description\nLearn everything you need to know, from beginner to master.\n\n#bottom\n:app-button[Start learning]{to=\"/docs/get-started/installation\"}\n::\n\n::home-features\n---\ncategory: Features\n---\n\n::section-content-item\n---\ntitle: Zero Configuration\ndescription: 'Start coding your app right away, Nuxt takes care of the rest.'\nimage: /img/home/discover/dx/zero-config.svg\n---\n::\n\n::section-content-item\n---\ntitle: File-system Routing\ndescription: 'Automatic routing and code-splitting for every page.'\nimage: /img/home/discover/dx/file-system-routing.svg\n---\n::\n\n::section-content-item\n---\ntitle: Rendering Modes\ndescription: 'Switch between static-site generation or on-demand server rendering.'\nimage: /img/home/discover/dx/hybrid.svg\n---\n::\n\n::section-content-item\n---\ntitle: Data Fetching\ndescription: 'Fetch your content from any source in your Vue components, SSR ready.'\nimage: /img/home/discover/dx/fetch.svg\n---\n::\n\n::section-content-item\n---\ntitle: Strong Conventions\ndescription: 'Efficient teamwork with a strong directory structure and conventions.'\nimage: /img/home/discover/dx/conventions.svg\n---\n::\n\n::section-content-item\n---\ntitle: SEO Friendly\ndescription: 'Meta tag management and faster time-to-content for great indexing.'\nimage: /img/home/discover/dx/seo.svg\n---\n::\n\n::section-content-item\n---\ntitle: Components Auto-import\ndescription: 'Use your components, Nuxt will import them with smart code-splitting.'\nimage: /img/home/discover/dx/auto-inject.svg\n---\n::\n\n::section-content-item\n---\ntitle: Modules Ecosystem\ndescription: 'Extend your app with 160+ Nuxt modules and create your own.'\nimage: /img/home/discover/dx/modular.svg\n---\n::\n\n#title\nIntuitive [D]{.text-primary}eveloper E[x]{.text-primary}perience\n\n#description\nNuxt is shipped with plenty of features to boost developer productivity and the end user experience.\n::\n\n::home-discover-partners\n---\ncategory: Partners\n---\n\n#title\nSustainable [_Development_]{.text-primary}\n\n#description\nNuxt development is carried out by passionate developers, but the amount of effort needed to maintain and develop new features is not sustainable without proper financial backing. We are thankful for our sponsors and partners, who help make Nuxt possible.<br>\n\n#partners-card\n  ::home-partners-card\n  ---\n  icon: technology.svg\n  category: technology\n  ---\n  #title\n  Technology partners\n\n  #description\n  Technology partners offer services that empower Nuxt developers, such as CMS, Hosting, Database, and more.\n\n  #button\n  Discover our technology partners\n  ::\n\n  ::home-partners-card\n  ---\n  icon: agency.svg\n  category: agency\n  ---\n  #title\n  Agency partners\n\n  #description\n  Agency partners are trusted web and consulting agencies that can provide Nuxt development and support for your projects.\n\n  #button\n  Find a Nuxt expert\n  ::\n\n#bottom\n  :app-button[Become a partner]{href=\"mailto:partners@nuxtlabs.com\"}\n::\n\n::home-learn-guides\n---\ncategory: Learn\n---\n\n::section-content-item\n---\ntitle: Documentation\ndescription: 'Discover Nuxt concepts and find a complete API reference.'\nimage: /img/home/learn/guides/gem-1.svg\nto: '/docs/get-started/installation'\nhoverClass: 'hover:bg-sky-darker'\n---\n::\n\n::section-content-item\n---\ntitle: Examples\ndescription: \"Learn by examples produced by the community.\"\nimage: /img/home/learn/guides/gem-2.svg\nto: '/examples'\nhoverClass: 'hover:bg-sky-darker'\n---\n::\n\n::section-content-item\n---\ntitle: Releases\ndescription: 'Find out what has changed before upgrading.'\nimage: /img/home/learn/guides/gem-3.svg\nto: '/releases'\nhoverClass: 'hover:bg-sky-darker'\n---\n::\n\n::section-content-item\n---\ntitle: Master Courses\ndescription: 'Watch a complete series of videos to learn Nuxt with our partner Vue School.'\nimage: /img/home/learn/guides/gem-4.svg\nto: 'https://masteringnuxt.com/?utm_source=nuxt&utm_medium=link&utm_campaign=nsite'\nhoverClass: 'hover:bg-sky-darker'\n---\n::\n\n#title\nFollow our [_Guides_]{.text-primary}\n\n#description\nFrom an idea to a masterpiece, guides take you on the path to becoming a Nuxter.\n::\n\n::home-explore\n---\ncategory: Explore\n---\n\n::section-content-item\n---\ntitle: 'Deployments'\ndescription: 'Extend and automate your workflow by using deployments for your favorite tools.'\nimage: '/img/home/explore/gem-explore-1.svg'\nto: '/deployments'\nhoverClass: 'hover:bg-sky-surface'\n---\n::\n::section-content-item\n---\ntitle: 'Modules'\ndescription: 'Discover our list of modules to supercharge your Nuxt project. Created by the Nuxt team and community.'\nimage: '/img/home/explore/gem-explore-2.svg'\nto: 'https://modules.nuxtjs.org'\nhoverClass: 'hover:bg-sky-surface'\n---\n::\n::section-content-item\n---\ntitle: 'Themes'\ndescription: 'See how a real world application is built using the Nuxt stack with the themes built by our partners.'\nimage: '/img/home/explore/gem-explore-3.svg'\nto: '/themes'\nhoverClass: 'hover:bg-sky-surface'\n---\n::\n\n#title\nMoving forward? So much to [_Explore_]{.text-primary}\n\n#description\nDiscover powerful modules, integrate with your favorite providers and start quickly with themes.\n::\n\n::home-community\n---\ncategory: Community\nannouncementsCategory: Announcements\neventsCategory: Events\narticleLinkTitle: Get infos\n---\n\n#title\nSharing is [Caring]{.text-sky-lighter}\n\n#description\nDiscover articles from the framework team and community about Nuxt. Tips and tricks included!\n::\n\n::home-testimonials\n---\ncategory: Community\n---\n#title\nTestimonials\n\n#description\nLearn what the experts love about Nuxt.\n\n#testimonials\n  :::testimonials\n  ---\n  home: true\n  ---\n  :::\n::\n","ast":{"type":"root","children":[{"type":"element","tag":"home-hero","props":{},"children":[{"type":"element","tag":"template","props":{"v-slot:title":""},"children":[{"type":"element","tag":"prose-paragraph","props":{},"children":[{"type":"text","value":"The Intuitive Vue"},{"type":"element","tag":"br","props":{},"children":[]},{"type":"text","value":"Framework"}]}],"content":[{"type":"element","tag":"prose-paragraph","props":{},"children":[{"type":"text","value":"The Intuitive Vue"},{"type":"element","tag":"br","props":{},"children":[]},{"type":"text","value":"Framework"}]}]},{"type":"element","tag":"template","props":{"v-slot:description":""},"children":[{"type":"element","tag":"prose-paragraph","props":{},"children":[{"type":"text","value":"Build your next Vue.js application with confidence using Nuxt."},{"type":"element","tag":"br","props":{"className":["hidden","sm:block"]},"children":[]},{"type":"text","value":" An open source framework making web development simple and powerful."}]}],"content":[{"type":"element","tag":"prose-paragraph","props":{},"children":[{"type":"text","value":"Build your next Vue.js application with confidence using Nuxt."},{"type":"element","tag":"br","props":{"className":["hidden","sm:block"]},"children":[]},{"type":"text","value":" An open source framework making web development simple and powerful."}]}]},{"type":"element","tag":"template","props":{"v-slot:primary-button":""},"children":[{"type":"element","tag":"app-button","props":{"href":"https://github.com/nuxt/nuxt.js","extraClass":"text-white bg-sky-black hover:bg-sky-darker leading-4","icon":"IconGitHub"},"children":[{"type":"text","value":"39K+ GitHub stars"}]}],"content":[{"type":"element","tag":"app-button","props":{"href":"https://github.com/nuxt/nuxt.js","extraClass":"text-white bg-sky-black hover:bg-sky-darker leading-4","icon":"IconGitHub"},"children":[{"type":"text","value":"39K+ GitHub stars"}]}]},{"type":"element","tag":"template","props":{"v-slot:secondary-button":""},"children":[{"type":"element","tag":"app-button","props":{"to":"/docs/get-started/installation"},"children":[{"type":"text","value":"Get started"}]}],"content":[{"type":"element","tag":"app-button","props":{"to":"/docs/get-started/installation"},"children":[{"type":"text","value":"Get started"}]}]}]},{"type":"text","value":"\n"},{"type":"element","tag":"home-learn-master","props":{"category":"Learn"},"children":[{"type":"element","tag":"template","props":{"v-slot:title":""},"children":[{"type":"element","tag":"prose-paragraph","props":{},"children":[{"type":"element","tag":"span","props":{"className":["text-primary"]},"children":[{"type":"text","value":"Easy"}]},{"type":"text","value":" to learn. "},{"type":"element","tag":"span","props":{"className":["text-primary"]},"children":[{"type":"text","value":"Easy"}]},{"type":"text","value":" to master"}]}],"content":[{"type":"element","tag":"prose-paragraph","props":{},"children":[{"type":"element","tag":"span","props":{"className":["text-primary"]},"children":[{"type":"text","value":"Easy"}]},{"type":"text","value":" to learn. "},{"type":"element","tag":"span","props":{"className":["text-primary"]},"children":[{"type":"text","value":"Easy"}]},{"type":"text","value":" to master"}]}]},{"type":"element","tag":"template","props":{"v-slot:description":""},"children":[{"type":"element","tag":"prose-paragraph","props":{},"children":[{"type":"text","value":"Learn everything you need to know, from beginner to master."}]}],"content":[{"type":"element","tag":"prose-paragraph","props":{},"children":[{"type":"text","value":"Learn everything you need to know, from beginner to master."}]}]},{"type":"element","tag":"template","props":{"v-slot:bottom":""},"children":[{"type":"element","tag":"app-button","props":{"to":"/docs/get-started/installation"},"children":[{"type":"text","value":"Start learning"}]}],"content":[{"type":"element","tag":"app-button","props":{"to":"/docs/get-started/installation"},"children":[{"type":"text","value":"Start learning"}]}]}]},{"type":"text","value":"\n"},{"type":"element","tag":"home-features","props":{"category":"Features"},"children":[{"type":"element","tag":"section-content-item","props":{"description":"Start coding your app right away, Nuxt takes care of the rest.","image":"/img/home/discover/dx/zero-config.svg","title":"Zero Configuration"},"children":[]},{"type":"element","tag":"section-content-item","props":{"description":"Automatic routing and code-splitting for every page.","image":"/img/home/discover/dx/file-system-routing.svg","title":"File-system Routing"},"children":[]},{"type":"element","tag":"section-content-item","props":{"description":"Switch between static-site generation or on-demand server rendering.","image":"/img/home/discover/dx/hybrid.svg","title":"Rendering Modes"},"children":[]},{"type":"element","tag":"section-content-item","props":{"description":"Fetch your content from any source in your Vue components, SSR ready.","image":"/img/home/discover/dx/fetch.svg","title":"Data Fetching"},"children":[]},{"type":"element","tag":"section-content-item","props":{"description":"Efficient teamwork with a strong directory structure and conventions.","image":"/img/home/discover/dx/conventions.svg","title":"Strong Conventions"},"children":[]},{"type":"element","tag":"section-content-item","props":{"description":"Meta tag management and faster time-to-content for great indexing.","image":"/img/home/discover/dx/seo.svg","title":"SEO Friendly"},"children":[]},{"type":"element","tag":"section-content-item","props":{"description":"Use your components, Nuxt will import them with smart code-splitting.","image":"/img/home/discover/dx/auto-inject.svg","title":"Components Auto-import"},"children":[]},{"type":"element","tag":"section-content-item","props":{"description":"Extend your app with 160+ Nuxt modules and create your own.","image":"/img/home/discover/dx/modular.svg","title":"Modules Ecosystem"},"children":[]},{"type":"element","tag":"template","props":{"v-slot:title":""},"children":[{"type":"element","tag":"prose-paragraph","props":{},"children":[{"type":"text","value":"Intuitive "},{"type":"element","tag":"span","props":{"className":["text-primary"]},"children":[{"type":"text","value":"D"}]},{"type":"text","value":"eveloper E"},{"type":"element","tag":"span","props":{"className":["text-primary"]},"children":[{"type":"text","value":"x"}]},{"type":"text","value":"perience"}]}],"content":[{"type":"element","tag":"prose-paragraph","props":{},"children":[{"type":"text","value":"Intuitive "},{"type":"element","tag":"span","props":{"className":["text-primary"]},"children":[{"type":"text","value":"D"}]},{"type":"text","value":"eveloper E"},{"type":"element","tag":"span","props":{"className":["text-primary"]},"children":[{"type":"text","value":"x"}]},{"type":"text","value":"perience"}]}]},{"type":"element","tag":"template","props":{"v-slot:description":""},"children":[{"type":"element","tag":"prose-paragraph","props":{},"children":[{"type":"text","value":"Nuxt is shipped with plenty of features to boost developer productivity and the end user experience."}]}],"content":[{"type":"element","tag":"prose-paragraph","props":{},"children":[{"type":"text","value":"Nuxt is shipped with plenty of features to boost developer productivity and the end user experience."}]}]}]},{"type":"text","value":"\n"},{"type":"element","tag":"home-discover-partners","props":{"category":"Partners"},"children":[{"type":"element","tag":"template","props":{"v-slot:title":""},"children":[{"type":"element","tag":"prose-paragraph","props":{},"children":[{"type":"text","value":"Sustainable "},{"type":"element","tag":"span","props":{"className":["text-primary"]},"children":[{"type":"element","tag":"prose-em","props":{},"children":[{"type":"text","value":"Development"}]}]}]}],"content":[{"type":"element","tag":"prose-paragraph","props":{},"children":[{"type":"text","value":"Sustainable "},{"type":"element","tag":"span","props":{"className":["text-primary"]},"children":[{"type":"element","tag":"prose-em","props":{},"children":[{"type":"text","value":"Development"}]}]}]}]},{"type":"element","tag":"template","props":{"v-slot:description":""},"children":[{"type":"element","tag":"prose-paragraph","props":{},"children":[{"type":"text","value":"Nuxt development is carried out by passionate developers, but the amount of effort needed to maintain and develop new features is not sustainable without proper financial backing. We are thankful for our sponsors and partners, who help make Nuxt possible."},{"type":"element","tag":"br","props":{},"children":[]}]}],"content":[{"type":"element","tag":"prose-paragraph","props":{},"children":[{"type":"text","value":"Nuxt development is carried out by passionate developers, but the amount of effort needed to maintain and develop new features is not sustainable without proper financial backing. We are thankful for our sponsors and partners, who help make Nuxt possible."},{"type":"element","tag":"br","props":{},"children":[]}]}]},{"type":"element","tag":"template","props":{"v-slot:partners-card":""},"children":[{"type":"element","tag":"home-partners-card","props":{"category":"technology","icon":"technology.svg"},"children":[{"type":"element","tag":"template","props":{"v-slot:title":""},"children":[{"type":"element","tag":"prose-paragraph","props":{},"children":[{"type":"text","value":"Technology partners"}]}],"content":[{"type":"element","tag":"prose-paragraph","props":{},"children":[{"type":"text","value":"Technology partners"}]}]},{"type":"element","tag":"template","props":{"v-slot:description":""},"children":[{"type":"element","tag":"prose-paragraph","props":{},"children":[{"type":"text","value":"Technology partners offer services that empower Nuxt developers, such as CMS, Hosting, Database, and more."}]}],"content":[{"type":"element","tag":"prose-paragraph","props":{},"children":[{"type":"text","value":"Technology partners offer services that empower Nuxt developers, such as CMS, Hosting, Database, and more."}]}]},{"type":"element","tag":"template","props":{"v-slot:button":""},"children":[{"type":"element","tag":"prose-paragraph","props":{},"children":[{"type":"text","value":"Discover our technology partners"}]}],"content":[{"type":"element","tag":"prose-paragraph","props":{},"children":[{"type":"text","value":"Discover our technology partners"}]}]}]},{"type":"element","tag":"home-partners-card","props":{"category":"agency","icon":"agency.svg"},"children":[{"type":"element","tag":"template","props":{"v-slot:title":""},"children":[{"type":"element","tag":"prose-paragraph","props":{},"children":[{"type":"text","value":"Agency partners"}]}],"content":[{"type":"element","tag":"prose-paragraph","props":{},"children":[{"type":"text","value":"Agency partners"}]}]},{"type":"element","tag":"template","props":{"v-slot:description":""},"children":[{"type":"element","tag":"prose-paragraph","props":{},"children":[{"type":"text","value":"Agency partners are trusted web and consulting agencies that can provide Nuxt development and support for your projects."}]}],"content":[{"type":"element","tag":"prose-paragraph","props":{},"children":[{"type":"text","value":"Agency partners are trusted web and consulting agencies that can provide Nuxt development and support for your projects."}]}]},{"type":"element","tag":"template","props":{"v-slot:button":""},"children":[{"type":"element","tag":"prose-paragraph","props":{},"children":[{"type":"text","value":"Find a Nuxt expert"}]}],"content":[{"type":"element","tag":"prose-paragraph","props":{},"children":[{"type":"text","value":"Find a Nuxt expert"}]}]}]}],"content":[{"type":"element","tag":"home-partners-card","props":{"category":"technology","icon":"technology.svg"},"children":[{"type":"element","tag":"template","props":{"v-slot:title":""},"children":[{"type":"element","tag":"prose-paragraph","props":{},"children":[{"type":"text","value":"Technology partners"}]}],"content":[{"type":"element","tag":"prose-paragraph","props":{},"children":[{"type":"text","value":"Technology partners"}]}]},{"type":"element","tag":"template","props":{"v-slot:description":""},"children":[{"type":"element","tag":"prose-paragraph","props":{},"children":[{"type":"text","value":"Technology partners offer services that empower Nuxt developers, such as CMS, Hosting, Database, and more."}]}],"content":[{"type":"element","tag":"prose-paragraph","props":{},"children":[{"type":"text","value":"Technology partners offer services that empower Nuxt developers, such as CMS, Hosting, Database, and more."}]}]},{"type":"element","tag":"template","props":{"v-slot:button":""},"children":[{"type":"element","tag":"prose-paragraph","props":{},"children":[{"type":"text","value":"Discover our technology partners"}]}],"content":[{"type":"element","tag":"prose-paragraph","props":{},"children":[{"type":"text","value":"Discover our technology partners"}]}]}]},{"type":"element","tag":"home-partners-card","props":{"category":"agency","icon":"agency.svg"},"children":[{"type":"element","tag":"template","props":{"v-slot:title":""},"children":[{"type":"element","tag":"prose-paragraph","props":{},"children":[{"type":"text","value":"Agency partners"}]}],"content":[{"type":"element","tag":"prose-paragraph","props":{},"children":[{"type":"text","value":"Agency partners"}]}]},{"type":"element","tag":"template","props":{"v-slot:description":""},"children":[{"type":"element","tag":"prose-paragraph","props":{},"children":[{"type":"text","value":"Agency partners are trusted web and consulting agencies that can provide Nuxt development and support for your projects."}]}],"content":[{"type":"element","tag":"prose-paragraph","props":{},"children":[{"type":"text","value":"Agency partners are trusted web and consulting agencies that can provide Nuxt development and support for your projects."}]}]},{"type":"element","tag":"template","props":{"v-slot:button":""},"children":[{"type":"element","tag":"prose-paragraph","props":{},"children":[{"type":"text","value":"Find a Nuxt expert"}]}],"content":[{"type":"element","tag":"prose-paragraph","props":{},"children":[{"type":"text","value":"Find a Nuxt expert"}]}]}]}]},{"type":"element","tag":"template","props":{"v-slot:bottom":""},"children":[{"type":"element","tag":"app-button","props":{"href":"mailto:partners@nuxtlabs.com"},"children":[{"type":"text","value":"Become a partner"}]}],"content":[{"type":"element","tag":"app-button","props":{"href":"mailto:partners@nuxtlabs.com"},"children":[{"type":"text","value":"Become a partner"}]}]}]},{"type":"text","value":"\n"},{"type":"element","tag":"home-learn-guides","props":{"category":"Learn"},"children":[{"type":"element","tag":"section-content-item","props":{"description":"Discover Nuxt concepts and find a complete API reference.","image":"/img/home/learn/guides/gem-1.svg","title":"Documentation","hoverClass":"hover:bg-sky-darker","to":"/docs/get-started/installation"},"children":[]},{"type":"element","tag":"section-content-item","props":{"description":"Learn by examples produced by the community.","image":"/img/home/learn/guides/gem-2.svg","title":"Examples","hoverClass":"hover:bg-sky-darker","to":"/examples"},"children":[]},{"type":"element","tag":"section-content-item","props":{"description":"Find out what has changed before upgrading.","image":"/img/home/learn/guides/gem-3.svg","title":"Releases","hoverClass":"hover:bg-sky-darker","to":"/releases"},"children":[]},{"type":"element","tag":"section-content-item","props":{"description":"Watch a complete series of videos to learn Nuxt with our partner Vue School.","image":"/img/home/learn/guides/gem-4.svg","title":"Master Courses","hoverClass":"hover:bg-sky-darker","to":"https://masteringnuxt.com/?utm_source=nuxt&utm_medium=link&utm_campaign=nsite"},"children":[]},{"type":"element","tag":"template","props":{"v-slot:title":""},"children":[{"type":"element","tag":"prose-paragraph","props":{},"children":[{"type":"text","value":"Follow our "},{"type":"element","tag":"span","props":{"className":["text-primary"]},"children":[{"type":"element","tag":"prose-em","props":{},"children":[{"type":"text","value":"Guides"}]}]}]}],"content":[{"type":"element","tag":"prose-paragraph","props":{},"children":[{"type":"text","value":"Follow our "},{"type":"element","tag":"span","props":{"className":["text-primary"]},"children":[{"type":"element","tag":"prose-em","props":{},"children":[{"type":"text","value":"Guides"}]}]}]}]},{"type":"element","tag":"template","props":{"v-slot:description":""},"children":[{"type":"element","tag":"prose-paragraph","props":{},"children":[{"type":"text","value":"From an idea to a masterpiece, guides take you on the path to becoming a Nuxter."}]}],"content":[{"type":"element","tag":"prose-paragraph","props":{},"children":[{"type":"text","value":"From an idea to a masterpiece, guides take you on the path to becoming a Nuxter."}]}]}]},{"type":"text","value":"\n"},{"type":"element","tag":"home-explore","props":{"category":"Explore"},"children":[{"type":"element","tag":"section-content-item","props":{"description":"Extend and automate your workflow by using deployments for your favorite tools.","image":"/img/home/explore/gem-explore-1.svg","title":"Deployments","hoverClass":"hover:bg-sky-surface","to":"/deployments"},"children":[]},{"type":"element","tag":"section-content-item","props":{"description":"Discover our list of modules to supercharge your Nuxt project. Created by the Nuxt team and community.","image":"/img/home/explore/gem-explore-2.svg","title":"Modules","hoverClass":"hover:bg-sky-surface","to":"https://modules.nuxtjs.org"},"children":[]},{"type":"element","tag":"section-content-item","props":{"description":"See how a real world application is built using the Nuxt stack with the themes built by our partners.","image":"/img/home/explore/gem-explore-3.svg","title":"Themes","hoverClass":"hover:bg-sky-surface","to":"/themes"},"children":[]},{"type":"element","tag":"template","props":{"v-slot:title":""},"children":[{"type":"element","tag":"prose-paragraph","props":{},"children":[{"type":"text","value":"Moving forward? So much to "},{"type":"element","tag":"span","props":{"className":["text-primary"]},"children":[{"type":"element","tag":"prose-em","props":{},"children":[{"type":"text","value":"Explore"}]}]}]}],"content":[{"type":"element","tag":"prose-paragraph","props":{},"children":[{"type":"text","value":"Moving forward? So much to "},{"type":"element","tag":"span","props":{"className":["text-primary"]},"children":[{"type":"element","tag":"prose-em","props":{},"children":[{"type":"text","value":"Explore"}]}]}]}]},{"type":"element","tag":"template","props":{"v-slot:description":""},"children":[{"type":"element","tag":"prose-paragraph","props":{},"children":[{"type":"text","value":"Discover powerful modules, integrate with your favorite providers and start quickly with themes."}]}],"content":[{"type":"element","tag":"prose-paragraph","props":{},"children":[{"type":"text","value":"Discover powerful modules, integrate with your favorite providers and start quickly with themes."}]}]}]},{"type":"text","value":"\n"},{"type":"element","tag":"home-community","props":{"announcementsCategory":"Announcements","articleLinkTitle":"Get infos","category":"Community","eventsCategory":"Events"},"children":[{"type":"element","tag":"template","props":{"v-slot:title":""},"children":[{"type":"element","tag":"prose-paragraph","props":{},"children":[{"type":"text","value":"Sharing is "},{"type":"element","tag":"span","props":{"className":["text-sky-lighter"]},"children":[{"type":"text","value":"Caring"}]}]}],"content":[{"type":"element","tag":"prose-paragraph","props":{},"children":[{"type":"text","value":"Sharing is "},{"type":"element","tag":"span","props":{"className":["text-sky-lighter"]},"children":[{"type":"text","value":"Caring"}]}]}]},{"type":"element","tag":"template","props":{"v-slot:description":""},"children":[{"type":"element","tag":"prose-paragraph","props":{},"children":[{"type":"text","value":"Discover articles from the framework team and community about Nuxt. Tips and tricks included!"}]}],"content":[{"type":"element","tag":"prose-paragraph","props":{},"children":[{"type":"text","value":"Discover articles from the framework team and community about Nuxt. Tips and tricks included!"}]}]}]},{"type":"text","value":"\n"},{"type":"element","tag":"home-testimonials","props":{"category":"Community"},"children":[{"type":"element","tag":"template","props":{"v-slot:title":""},"children":[{"type":"element","tag":"prose-paragraph","props":{},"children":[{"type":"text","value":"Testimonials"}]}],"content":[{"type":"element","tag":"prose-paragraph","props":{},"children":[{"type":"text","value":"Testimonials"}]}]},{"type":"element","tag":"template","props":{"v-slot:description":""},"children":[{"type":"element","tag":"prose-paragraph","props":{},"children":[{"type":"text","value":"Learn what the experts love about Nuxt."}]}],"content":[{"type":"element","tag":"prose-paragraph","props":{},"children":[{"type":"text","value":"Learn what the experts love about Nuxt."}]}]},{"type":"element","tag":"template","props":{"v-slot:testimonials":""},"children":[{"type":"element","tag":"testimonials","props":{":home":"true"},"children":[]}],"content":[{"type":"element","tag":"testimonials","props":{":home":"true"},"children":[]}]}]}]},"toc":{"title":"","searchDepth":2,"depth":2,"links":[]}}}