{"key":"content:zh:design:index.md","generatedAt":"2022-04-21T12:09:59.636Z","mtime":"2022-04-21T12:09:59.629Z","slug":"","title":"Design Kit","position":"999999990000","to":"/design","draft":false,"page":true,"language":"zh","template":"blank","description":"Learn how to use Nuxt logos, colors and fonts and download the design kit.","layout":{"fluid":true},"navigation":false,"empty":false,"body":{"raw":"---\ntemplate: blank\ntitle: 'Design Kit'\ndescription: 'Learn how to use Nuxt logos, colors and fonts and download the design kit.'\nlayout:\n  fluid: true\nnavigation: false\n---\n::design-hero\n---\ntitle: Design Kit\ndescription: \"Nuxt is an MIT licensed open source project and completely free to use.\nYou can freely use our logos as long as you mention Nuxt and link to nuxtjs.org.\"\nbutton: Download Design Kit\n---\n::\n\n::design-sections\n\n::design-section\n#title\nMonograms\n\n#description\nOur logo is made from two elements: the triangular mountains and the wordmark. In most cases, they should appear together as the opposite master lockup shows. The triangular mountains can be used on their own as an icon, profile picture or badge, but the wordmark should never be used without this symbol on the side.\n\n#sectionComponent\n  :::design-logos\n  ---\n  type: monogram\n  ---\n  :::\n::\n\n::design-section\n#title\nLogos\n\n#sectionComponent\n  :::design-logos\n  ---\n  type: logos\n  ---\n  :::\n::\n\n::design-section\n#title\nPrimary colors\n\n#description\nOur colours have been carefully considered to work in harmony and consistency across various media. When creating Nuxt communications, use the colour values shown on the following pages to make sure your designs stay on-brand. This nature-inspired primary colour palette should be used in all of our formal company related communications.\n\n#sectionComponent\n  :::design-colors\n  ---\n  buttonText: Download Color System\n  ---\n  :::\n::\n\n::design-section\n#title\nTypography\n\n#description\nOur brand typeface is DM Sans by Colophon Foundry for Google. This open-source typeface was chosen for its\ncombination of smoothness and structure. Its geometric shapes and soft transitions will bring clarity and openness\nto our texts. Also, it’s open availability will let other members of the Nuxt community incorporate it into\ntheir work.\n\n#sectionComponent\n  :::design-typography\n::\n::\n","ast":{"type":"root","children":[{"type":"element","tag":"design-hero","props":{"button":"Download Design Kit","description":"Nuxt is an MIT licensed open source project and completely free to use. You can freely use our logos as long as you mention Nuxt and link to nuxtjs.org.","title":"Design Kit"},"children":[]},{"type":"text","value":"\n"},{"type":"element","tag":"design-sections","props":{},"children":[{"type":"element","tag":"design-section","props":{},"children":[{"type":"element","tag":"template","props":{"v-slot:title":""},"children":[{"type":"element","tag":"prose-paragraph","props":{},"children":[{"type":"text","value":"Monograms"}]}],"content":[{"type":"element","tag":"prose-paragraph","props":{},"children":[{"type":"text","value":"Monograms"}]}]},{"type":"element","tag":"template","props":{"v-slot:description":""},"children":[{"type":"element","tag":"prose-paragraph","props":{},"children":[{"type":"text","value":"Our logo is made from two elements: the triangular mountains and the wordmark. In most cases, they should appear together as the opposite master lockup shows. The triangular mountains can be used on their own as an icon, profile picture or badge, but the wordmark should never be used without this symbol on the side."}]}],"content":[{"type":"element","tag":"prose-paragraph","props":{},"children":[{"type":"text","value":"Our logo is made from two elements: the triangular mountains and the wordmark. In most cases, they should appear together as the opposite master lockup shows. The triangular mountains can be used on their own as an icon, profile picture or badge, but the wordmark should never be used without this symbol on the side."}]}]},{"type":"element","tag":"template","props":{"v-slot:sectionComponent":""},"children":[{"type":"element","tag":"design-logos","props":{"type":"monogram"},"children":[]}],"content":[{"type":"element","tag":"design-logos","props":{"type":"monogram"},"children":[]}]}]},{"type":"element","tag":"design-section","props":{},"children":[{"type":"element","tag":"template","props":{"v-slot:title":""},"children":[{"type":"element","tag":"prose-paragraph","props":{},"children":[{"type":"text","value":"Logos"}]}],"content":[{"type":"element","tag":"prose-paragraph","props":{},"children":[{"type":"text","value":"Logos"}]}]},{"type":"element","tag":"template","props":{"v-slot:sectionComponent":""},"children":[{"type":"element","tag":"design-logos","props":{"type":"logos"},"children":[]}],"content":[{"type":"element","tag":"design-logos","props":{"type":"logos"},"children":[]}]}]},{"type":"element","tag":"design-section","props":{},"children":[{"type":"element","tag":"template","props":{"v-slot:title":""},"children":[{"type":"element","tag":"prose-paragraph","props":{},"children":[{"type":"text","value":"Primary colors"}]}],"content":[{"type":"element","tag":"prose-paragraph","props":{},"children":[{"type":"text","value":"Primary colors"}]}]},{"type":"element","tag":"template","props":{"v-slot:description":""},"children":[{"type":"element","tag":"prose-paragraph","props":{},"children":[{"type":"text","value":"Our colours have been carefully considered to work in harmony and consistency across various media. When creating Nuxt communications, use the colour values shown on the following pages to make sure your designs stay on-brand. This nature-inspired primary colour palette should be used in all of our formal company related communications."}]}],"content":[{"type":"element","tag":"prose-paragraph","props":{},"children":[{"type":"text","value":"Our colours have been carefully considered to work in harmony and consistency across various media. When creating Nuxt communications, use the colour values shown on the following pages to make sure your designs stay on-brand. This nature-inspired primary colour palette should be used in all of our formal company related communications."}]}]},{"type":"element","tag":"template","props":{"v-slot:sectionComponent":""},"children":[{"type":"element","tag":"design-colors","props":{"buttonText":"Download Color System"},"children":[]}],"content":[{"type":"element","tag":"design-colors","props":{"buttonText":"Download Color System"},"children":[]}]}]},{"type":"element","tag":"design-section","props":{},"children":[{"type":"element","tag":"template","props":{"v-slot:title":""},"children":[{"type":"element","tag":"prose-paragraph","props":{},"children":[{"type":"text","value":"Typography"}]}],"content":[{"type":"element","tag":"prose-paragraph","props":{},"children":[{"type":"text","value":"Typography"}]}]},{"type":"element","tag":"template","props":{"v-slot:description":""},"children":[{"type":"element","tag":"prose-paragraph","props":{},"children":[{"type":"text","value":"Our brand typeface is DM Sans by Colophon Foundry for Google. This open-source typeface was chosen for its\ncombination of smoothness and structure. Its geometric shapes and soft transitions will bring clarity and openness\nto our texts. Also, it’s open availability will let other members of the Nuxt community incorporate it into\ntheir work."}]}],"content":[{"type":"element","tag":"prose-paragraph","props":{},"children":[{"type":"text","value":"Our brand typeface is DM Sans by Colophon Foundry for Google. This open-source typeface was chosen for its\ncombination of smoothness and structure. Its geometric shapes and soft transitions will bring clarity and openness\nto our texts. Also, it’s open availability will let other members of the Nuxt community incorporate it into\ntheir work."}]}]},{"type":"element","tag":"template","props":{"v-slot:sectionComponent":""},"children":[{"type":"element","tag":"design-typography","props":{},"children":[]}],"content":[{"type":"element","tag":"design-typography","props":{},"children":[]}]}]}]}]},"toc":{"title":"","searchDepth":2,"depth":2,"links":[]}}}