{"key":"content:en:themes:index.md","generatedAt":"2022-04-23T04:16:18.285Z","mtime":"2022-04-23T04:16:18.279Z","slug":"","title":"Themes","position":"999999990000","to":"/themes","draft":false,"page":true,"language":"en","template":"blog","description":"See how a real world application is built using the Nuxt stack with the themes built by our partners.","empty":false,"body":{"raw":"---\ntemplate: blog\ntitle: Themes\ndescription: 'See how a real world application is built using the Nuxt stack with the themes built by our partners.'\n---\n::themes-list\n---\nthemes:\n  one:\n    title: Nuxt Argon Dashboard PRO\n    description: Nuxt Argon Dashboard PRO is built with over 200 individual components, giving you the freedom of choosing and combining.\n    image: /img/themes/argon_dashboard_pro.jpg\n    slug: one\n    price: $99\n    href: https://www.creative-tim.com/product/nuxt-argon-dashboard-pro?partner=120213\n  two:\n    title: Nuxt Argon Dashboard PRO Laravel\n    description: \"All the functionality of a lightweight CMS out of the box, built using two of the most popular frameworks today: Nuxt and Laravel.\"\n    image: /img/themes/argon_dashboard_pro_laravel.jpg\n    slug: two\n    price: $149\n    href: https://www.creative-tim.com/product/nuxt-argon-dashboard-pro-laravel?partner=120213\n  three:\n    title: Nuxt Now UI Kit\n    description: A premium responsive Bootstrap 4 kit provided by Invision and Creative Tim. It is a beautiful cross-platform UI kit featuring over 1000+ elements and 11 templates.\n    image: /img/themes/nuxt_now_ui_kit.jpg\n    slug: three\n    price: $89\n    href: https://www.creative-tim.com/product/nuxt-now-ui-kit-pro?partner=120213\n  four:\n    title: Nuxt Black Dashboard PRO\n    description: \"A beautiful Bootstrap 4 Admin Dashboard that comes in 2 versions: Dark and Light Mode.\"\n    image: /img/themes/nuxt_black_dashboard_pro.jpg\n    slug: four\n    price: $79\n    href: https://www.creative-tim.com/product/nuxt-black-dashboard-pro?partner=120213\n  five:\n    title: Nuxt Scutum Dashboard\n    description: Scutum Admin is a professional HTML5/CSS3 Material Design template based on UIkit Framework (v3) and Nuxt.\n    image: /img/themes/scutum_dashboard.jpg\n    slug: five\n    price: $26\n    href: https://1.envato.market/scutum-nuxt\n---\n::\n","ast":{"type":"root","children":[{"type":"element","tag":"themes-list","props":{":themes":"{\"one\":{\"title\":\"Nuxt Argon Dashboard PRO\",\"description\":\"Nuxt Argon Dashboard PRO is built with over 200 individual components, giving you the freedom of choosing and combining.\",\"image\":\"/img/themes/argon_dashboard_pro.jpg\",\"slug\":\"one\",\"price\":\"$99\",\"href\":\"https://www.creative-tim.com/product/nuxt-argon-dashboard-pro?partner=120213\"},\"two\":{\"title\":\"Nuxt Argon Dashboard PRO Laravel\",\"description\":\"All the functionality of a lightweight CMS out of the box, built using two of the most popular frameworks today: Nuxt and Laravel.\",\"image\":\"/img/themes/argon_dashboard_pro_laravel.jpg\",\"slug\":\"two\",\"price\":\"$149\",\"href\":\"https://www.creative-tim.com/product/nuxt-argon-dashboard-pro-laravel?partner=120213\"},\"three\":{\"title\":\"Nuxt Now UI Kit\",\"description\":\"A premium responsive Bootstrap 4 kit provided by Invision and Creative Tim. It is a beautiful cross-platform UI kit featuring over 1000+ elements and 11 templates.\",\"image\":\"/img/themes/nuxt_now_ui_kit.jpg\",\"slug\":\"three\",\"price\":\"$89\",\"href\":\"https://www.creative-tim.com/product/nuxt-now-ui-kit-pro?partner=120213\"},\"four\":{\"title\":\"Nuxt Black Dashboard PRO\",\"description\":\"A beautiful Bootstrap 4 Admin Dashboard that comes in 2 versions: Dark and Light Mode.\",\"image\":\"/img/themes/nuxt_black_dashboard_pro.jpg\",\"slug\":\"four\",\"price\":\"$79\",\"href\":\"https://www.creative-tim.com/product/nuxt-black-dashboard-pro?partner=120213\"},\"five\":{\"title\":\"Nuxt Scutum Dashboard\",\"description\":\"Scutum Admin is a professional HTML5/CSS3 Material Design template based on UIkit Framework (v3) and Nuxt.\",\"image\":\"/img/themes/scutum_dashboard.jpg\",\"slug\":\"five\",\"price\":\"$26\",\"href\":\"https://1.envato.market/scutum-nuxt\"}}"},"children":[]}]},"toc":{"title":"","searchDepth":2,"depth":2,"links":[]}}}